naver/__init__.py
naver/naver_searcher.py
SearchPackage-1.0.0.0.dist-info/METADATA
SearchPackage-1.0.0.0.dist-info/WHEEL
SearchPackage-1.0.0.0.dist-info/top_level.txt
SearchPackage-1.0.0.0.dist-info/RECORD
