Metadata-Version: 2.1
Name: SearchPackage
Version: 1.0.0.0
Summary: A package for searching
Home-page: https://eu4ng.tistory.com
Author: Joon Chung
Author-email: abcdefjoon@naver.com
License: MIT
Platform: UNKNOWN
Requires-Python: >=3
